{
	"design__io": 45,
	"design__die__area": 16000,
	"design__core__area": 13783.7,
	"design__instance__count": 298,
	"design__instance__area": 5334.34,
	"design__instance__count__stdcell": 298,
	"design__instance__area__stdcell": 5334.34,
	"design__instance__count__macros": 0,
	"design__instance__area__macros": 0,
	"design__instance__utilization": 0.387004,
	"design__instance__utilization__stdcell": 0.387004,
	"design__instance__count__class:endcap_cell": 46,
	"design__instance__count__class:fill_cell": 379,
	"design__instance__count__class:tap_cell": 87,
	"design__instance__count__class:tie_cell": 33,
	"design__instance__count__class:standard_cell": 132,
	"flow__warnings__count": 1,
	"flow__errors__count": 0
}