{
    "time": {
        "cpu_time_user": "00:00:01.919",
        "cpu_time_system": "00:00:00.260",
        "runtime": "00:00:02.440",
        "cpu_time_iowait": "00:00:00.000"
    },
    "peak_resources": {
        "cpu_percent": 108.5,
        "memory_rss": "137MiB",
        "memory_vms": "152MiB",
        "threads": 1
    },
    "avg_resources": {
        "cpu_percent": 82.41153846153848,
        "memory_rss": "87MiB",
        "memory_vms": "101MiB",
        "threads": 0.9615384615384616
    }
}